pymixology/__init__.py
pymixology/exceptions.py
pymixology/data/cocktails.json
pymixology/inventory/__init__.py
pymixology/inventory/items.py
pymixology/inventory/manager.py
pymixology/recipes/__init__.py
pymixology/recipes/catalog.py
pymixology/recipes/tools.py
pymixology/recommendation/__init__.py
pymixology/recommendation/preference.py
pymixology/recommendation/suggester.py
pymixology-0.1.0.dist-info/METADATA
pymixology-0.1.0.dist-info/WHEEL
pymixology-0.1.0.dist-info/top_level.txt
pymixology-0.1.0.dist-info/RECORD
