Metadata-Version: 2.4
Name: pymixology
Version: 0.1.0
Summary: A cocktail package
Home-page: 
Author: Data 533 Group 6
Author-email: 
Classifier: Programming Language :: Python :: 3
Classifier: License :: OSI Approved :: MIT License
Classifier: Operating System :: OS Independent
Requires-Python: >=3.7
Dynamic: author
Dynamic: classifier
Dynamic: description
Dynamic: description-content-type
Dynamic: requires-python
Dynamic: summary
